fasten/__init__.py
fasten/plugins/__init__.py
fasten/plugins/base.py
fasten/plugins/kafka.py
fasten-0.0.5.dist-info/LICENCE
fasten-0.0.5.dist-info/METADATA
fasten-0.0.5.dist-info/WHEEL
fasten-0.0.5.dist-info/top_level.txt
fasten-0.0.5.dist-info/RECORD
